pyad/__init__.py
pyad/adbase.py
pyad/adcomputer.py
pyad/adcontainer.py
pyad/addomain.py
pyad/adgroup.py
pyad/adobject.py
pyad/adquery.py
pyad/adsearch.py
pyad/aduser.py
pyad/pyad.py
pyad/pyadconstants.py
pyad/pyadexceptions.py
pyad/pyadutils.py
python_win_ad-0.6.3.dist-info/LICENSE
python_win_ad-0.6.3.dist-info/METADATA
python_win_ad-0.6.3.dist-info/WHEEL
python_win_ad-0.6.3.dist-info/top_level.txt
python_win_ad-0.6.3.dist-info/RECORD
