Metadata-Version: 2.1
Name: python-win-ad
Version: 0.6.3
Summary: An Object-Oriented Active Directory management framework built on ADSI
Home-page: https://github.com/jcarswell/pyad/
Author: Zakir Durumeric
Author-email: zakird@gmail.com
Maintainer: Josh Carswell
Maintainer-email: Josh.Carswell@thecarswells.ca
License: Apache License, Version 2.0
Project-URL: Documentation, https://jcarswell.github.io/pyad/
Project-URL: Issues, https://github.com/jcarswell/pyad/issues/
Keywords: python microsoft windows active directory AD adsi
Classifier: License :: OSI Approved :: Apache Software License
Classifier: Intended Audience :: System Administrators
Classifier: Natural Language :: English
Classifier: Operating System :: Microsoft :: Windows
Classifier: Topic :: System :: Systems Administration :: Authentication/Directory :: LDAP
Classifier: Programming Language :: Python :: 3
Classifier: Programming Language :: Python :: 3.8
Classifier: Programming Language :: Python :: 3.9
Classifier: Programming Language :: Python :: 3.10
Classifier: Programming Language :: Python :: 3.11
Obsoletes: pyad
Requires-Python: >=3.6
License-File: LICENSE
Requires-Dist: setuptools
Requires-Dist: pywin32
